.gitignore
CHANGES.txt
COPYRIGHT.txt
LICENSE.txt
README.txt
bootstrap.py
buildout.cfg
setup.py
src/sterch/__init__.py
src/sterch.scrapingtools.egg-info/PKG-INFO
src/sterch.scrapingtools.egg-info/SOURCES.txt
src/sterch.scrapingtools.egg-info/dependency_links.txt
src/sterch.scrapingtools.egg-info/namespace_packages.txt
src/sterch.scrapingtools.egg-info/not-zip-safe
src/sterch.scrapingtools.egg-info/requires.txt
src/sterch.scrapingtools.egg-info/top_level.txt
src/sterch/scrapingtools/__init__.py
src/sterch/scrapingtools/config.py
src/sterch/scrapingtools/configure.zcml
src/sterch/scrapingtools/courts.py
src/sterch/scrapingtools/decaptcher.py
src/sterch/scrapingtools/decorators.py
src/sterch/scrapingtools/entities.csv
src/sterch/scrapingtools/fullname.py
src/sterch/scrapingtools/handlers.py
src/sterch/scrapingtools/headers.py
src/sterch/scrapingtools/interfaces.py
src/sterch/scrapingtools/opener.py
src/sterch/scrapingtools/output.py
src/sterch/scrapingtools/synclist.py
src/sterch/scrapingtools/text.py
src/sterch/scrapingtools/worker.py
src/sterch/scrapingtools/writer.py