Metadata-Version: 1.0
Name: sterch.scrapingtools
Version: 0.5.1
Summary: Library for building scrapers
Home-page: http://sterch.net
Author: Polsha Maxim
Author-email: maxp@sterch.net
License: ZPL
Platform: UNKNOWN
